autoinsight/__init__.py
autoinsight/common/CustomTyping.py
autoinsight/common/EnumTypes.py
autoinsight/common/ObjectBase.py
autoinsight/common/SingletonMeta.py
autoinsight/common/Utils.py
autoinsight/common/__init__.py
autoinsight/common/models/BoundingBox.py
autoinsight/common/models/Box.py
autoinsight/common/models/Circle.py
autoinsight/common/models/Configuration.py
autoinsight/common/models/Event.py
autoinsight/common/models/IdentResult.py
autoinsight/common/models/Knowledge.py
autoinsight/common/models/Line.py
autoinsight/common/models/ModelBase.py
autoinsight/common/models/Point.py
autoinsight/common/models/Rectangle.py
autoinsight/common/models/ShapeBase.py
autoinsight/common/models/Size.py
autoinsight/common/models/__init__.py
autoinsight/communicator/__init__.py
autoinsight/data/__init__.py
autoinsight/data/autoinsight.yml
autoinsight/data/autoinsight.yml.schema.json
autoinsight/decorator/DecoratorBase.py
autoinsight/decorator/Delay.py
autoinsight/decorator/Log.py
autoinsight/decorator/Step.py
autoinsight/decorator/__init__.py
autoinsight/drivers/DriverBase.py
autoinsight/drivers/WindowApplicationDriver.py
autoinsight/drivers/WindowChromeDriver.py
autoinsight/drivers/__init__.py
autoinsight/event/EventBase.py
autoinsight/event/EventSource.py
autoinsight/event/__init__.py
autoinsight/event/handlers/__init__.py
autoinsight/event/source/__init__.py
autoinsight/extend/ExtendEnum.py
autoinsight/extend/ExtendPywinautoApplicationWindowSpecification.py
autoinsight/extend/__init__.py
autoinsight/ident/IdentObjectBase.py
autoinsight/ident/__init__.py
autoinsight/ident/context/BIOS.py
autoinsight/ident/context/BrowserBase.py
autoinsight/ident/context/BrowserContextBase.py
autoinsight/ident/context/BrowserTabBase.py
autoinsight/ident/context/BrowserWindowBase.py
autoinsight/ident/context/ChromeBrowserBase.py
autoinsight/ident/context/Command.py
autoinsight/ident/context/FormBase.py
autoinsight/ident/context/GUIApplicationBase.py
autoinsight-0.1.0.dist-info/LICENSE
autoinsight-0.1.0.dist-info/METADATA
autoinsight-0.1.0.dist-info/WHEEL
autoinsight-0.1.0.dist-info/top_level.txt
autoinsight-0.1.0.dist-info/RECORD
