Metadata-Version: 2.1
Name: autoinsight
Version: 0.1.0
Summary: A Simplified UI automation package
Home-page: https://github.com/shangerxin/autoinsight
Author: Erxin(Edwin) Shang
Author-email: author@example.com
Project-URL: Bug Tracker, https://github.com/shangerxin/autoinsight/issues
Classifier: Programming Language :: Python :: 3
Classifier: License :: OSI Approved :: Apache Software License
Classifier: Operating System :: Microsoft :: Windows
Requires-Python: >=3.6
License-File: LICENSE
Requires-Dist: pywinauto
Requires-Dist: pyyaml
Requires-Dist: pyautogui
Requires-Dist: opencv-python
Requires-Dist: pytesseract
Requires-Dist: wmi
Requires-Dist: pywin32
Requires-Dist: numpy
Requires-Dist: Pillow
Requires-Dist: winaudio
Requires-Dist: requests
Requires-Dist: schema
Requires-Dist: pydantic
Requires-Dist: colour-science
Requires-Dist: ultralytics
Requires-Dist: selenium
Requires-Dist: mss
